<?xml version="1.0" encoding="utf-8" standalone="yes"?>
<post>
  <author>Admin</author>
  <title>NRHS Band Program Newsletter – March 13, 2017</title>
  <description>Registration for 2017-2018 was DUE March 31st. If you have not registered, &amp;lt;a href="http://www.no</description>
  <content>&lt;p&gt;Registration for 2017-2018 was DUE March 31st. If you have not registered, &lt;a href="http://www.northroyaltonbandboosters.com/page/Band-Registration-Instructions"&gt;visit www.northroyaltonbandboosters.com to register&lt;/a&gt;!&lt;/p&gt;
 
&lt;p&gt;&lt;b&gt;LINKS you need to know:&lt;/b&gt;&lt;/p&gt;
&lt;ul&gt;
&lt;li&gt;&lt;a href="http://northroyaltonhighschoolband.com"&gt;Mr. Vitale’s Website&lt;/a&gt;&lt;/li&gt;
&lt;li&gt;&lt;a href="http://northroyaltonbandboosters.com"&gt;Band Booster’s Website&lt;/a&gt;&lt;/li&gt;
&lt;li&gt;&lt;a href="https://www.facebook.com/pages/North-Royalton-Band-Boosters/164850233634290"&gt;FaceBook North Royalton Band Boosters -- Like Us!!&lt;/a&gt;&lt;/li&gt;
 &lt;/ul&gt;
 
&lt;p&gt;&lt;b&gt;DATES you need to know:&lt;/b&gt;&lt;/p&gt;
&lt;ul&gt;
&lt;li&gt;April 24 – Band Booster Meeting – 7pm Media Center&lt;/li&gt;
&lt;li&gt;April 28/29 – High School Band Contest –WE NEED VOLUNTEERS (see below)&lt;/li&gt;
&lt;li&gt;April 28/29 – Easter Seals Drive (truck will be located near PAC)&lt;/li&gt;
 &lt;/ul&gt;
&lt;h3&gt;Band Registration&lt;/h3&gt;
&lt;p&gt;If you have not done so already, register your student for 2017-2018 Band Season!!! If you have question regarding registration, contact Amanda Kost – 440-864-6543&lt;/p&gt;
 
&lt;h3&gt;OMEA State Contest Volunteers Needed!&lt;/h3&gt;
&lt;p&gt;Thank you to everyone who has volunteered for States! WE NEED MORE HELP!!!! PLEASE consider helping us out! We have many opportunities for volunteering: Concessions, Sight Reading Door Monitors, Stage Crew/Gym &amp;amp; PAC Door Monitors, Program Sales, Hospitality, and Parking.&lt;/p&gt;
 
&lt;p&gt;The link to SignupGenius to volunteer is below: Please consider signing up for more than one time slot. You will be able to see your concert band member perform! Any questions, please contact Amanda Kost at 440-864-6543 or by email: &lt;a href="mailto:memandy@ameritech.net"&gt;memandy@ameritech.net&lt;/a&gt;. &lt;a href="http://www.signupgenius.com/go/805054EAFA729A02-omea1"&gt;Volunteer here.&lt;/a&gt;&lt;/p&gt;
 

&lt;h3&gt;Easter Seals&lt;/h3&gt;
&lt;p&gt;The Band Boosters will be partnering once again with Easter Seals! Our event will be running the SAME DAYS as State Contest. Since it was so successful, we will be parking the Easter Seals truck right outside the PAC. We do need volunteers to work the truck during the event. Please consider helping us out with this event! Any questions, please contact Holly 216-926-8836. &lt;a href="http://www.signupgenius.com/go/805054EAFA729A02-easter1"&gt;Volunteer here.&lt;/a&gt;&lt;/p&gt;
 

&lt;h3&gt;MAY 6 – Basket Raffle&lt;/h3&gt;
&lt;p&gt;Our annual Basket Raffle event will be MAY 6th and 3Spot in North Royalton. The 3Spot will be giving us the MAIN DINING room for our event this year! The ticket order form has gone out! Please send your ticket reservation to Becky Humes (address on ticket order form) or deposit in the white band box! Looking forward to a warm, spring event.&lt;/p&gt;</content>
  <ispublished>True</ispublished>
  <isdeleted>False</isdeleted>
  <iscommentsenabled>True</iscommentsenabled>
  <pubDate>2017-04-05 07:04:00</pubDate>
  <lastModified>2017-04-05 07:28:49</lastModified>
  <raters>0</raters>
  <rating>0</rating>
  <slug>nrhs-band-program-newsletter-march-13-20171</slug>
  <tags />
  <comments />
  <categories>
    <category>8fccb9f0-4993-489b-b231-4593baca27ee</category>
    <category>53e26df9-477c-4527-97c4-bce1fcd9688b</category>
  </categories>
  <notifications />
</post>