<?xml version="1.0" encoding="utf-8" standalone="yes"?>
<post>
  <author>Admin</author>
  <title>Market Day orders are due by this Friday</title>
  <description>Hi Band Boosters, 
 
Market Day orders are due by this Friday, February 6, 2015 at 11:00 pm at www.m</description>
  <content>&lt;p&gt;Hi Band Boosters, 
 
&lt;/p&gt;&lt;p&gt;&lt;b&gt;Market Day orders are due by this Friday, February 6, 2015 &lt;/b&gt;at &lt;b&gt;11:00 pm&lt;/b&gt; at &lt;a href="http://www.marketday.com"&gt;www.marketday.com&lt;/a&gt;.  &lt;b&gt;Pick up is Thursday, February 12, 2015 from 6:00 pm - 7:00 pm in Cafeteria #2&lt;/b&gt;. &lt;/p&gt;
 
&lt;p&gt;Please note that Market Day has changed our due date for orders to be the Friday before the sale instead of the Saturday before the sale by 11:00 pm.&lt;/p&gt;
 
&lt;p&gt;If you purchase anything this month, you will receive a $20 credit from Shutterfly, an on-line photo processing company. &lt;/p&gt;
 
&lt;p&gt;If you spend at least $90 this month and you will receive a free 60 count Cheese Ravioli when you enter promo code &lt;b&gt;FEBBONUS&lt;/b&gt;.
If you purchase three boxes of pre-portioned Cookie Dough flavors, you will receive one box of Chocolate Chunk Cookie Dough for free.&lt;/p&gt;
 
&lt;p&gt;Any questions, please contact Sue Galuska at &lt;a href="mailto:suegaluska@yahoo.com"&gt;suegaluska@yahoo.com&lt;/a&gt; or 440-582-4120.&lt;/p&gt;
 
&lt;p&gt;Thanks,&lt;br&gt;
Sue Galuska&lt;/p&gt;</content>
  <ispublished>True</ispublished>
  <isdeleted>False</isdeleted>
  <iscommentsenabled>True</iscommentsenabled>
  <pubDate>2015-02-04 20:02:00</pubDate>
  <lastModified>2015-02-04 20:23:14</lastModified>
  <raters>0</raters>
  <rating>0</rating>
  <slug>market-day-orders-are-due-by-this-friday</slug>
  <tags />
  <comments />
  <categories>
    <category>04fc31b2-00cd-4a3d-ae40-f49af9a917eb</category>
    <category>8a8649e2-a13d-47f8-abcb-7c344cb83e51</category>
  </categories>
  <notifications />
</post>