<?xml version="1.0" encoding="utf-8" standalone="yes"?>
<post>
  <author>Admin</author>
  <title>Band T-shirt, Band Polo and Marching Band Shoe Purchase Info &amp; More</title>
  <description>Hello Band Families!
 
Even though the school year has not ended, we need to start getting ready for</description>
  <content>&lt;p&gt;Hello Band Families!&lt;/p&gt;
 
&lt;p&gt;Even though the school year has not ended, we need to start getting ready for the upcoming marching season!!&lt;/p&gt;
 
&lt;p&gt;Mr. Vitale has posted both the Band Calendar AND the Band Camp Calendar on &lt;a href="http://www.northroyaltonhighschoolband.com"&gt;his website&lt;/a&gt;.&lt;/p&gt;
 
&lt;p&gt;Look under Forms and PDFs to find his calendar!&lt;/p&gt;
 
&lt;p&gt;&lt;b&gt;Important Booster dates to remember:&lt;/b&gt;&lt;/p&gt;
&lt;ul&gt; 
&lt;li&gt;&lt;b&gt;June 13&lt;/b&gt; &lt;b&gt;-14&lt;/b&gt; 8:00 – 8:30pm Tshirt ($10) and Polo ($20) Sale&lt;br&gt;Cafeteria 2&lt;br&gt;Cash or Check only&lt;/li&gt;
 
&lt;li&gt;&lt;b&gt;Aug 9&lt;/b&gt;&amp;nbsp;-&amp;nbsp;6:15pm New Parent Meeting – WELCOME!&lt;/li&gt;
 &lt;/ul&gt;
&lt;p&gt;If you have not ordered your Marching Shoes yet, &lt;a href="/FILES%2f2017%2f05%2fRMC-MarchingBandShoes.pdf.axdx"&gt;&lt;b&gt;please see the attached flyer&lt;/b&gt;&lt;/a&gt;…. Order early to receive the best price!&lt;/p&gt;
 
&lt;p&gt;Just a heads up, for Parent Preview Night AND the Homedays Parade, you will need Khaki pants (not Cargo pants) along with a Black Belt, your Marching Shoes, Black Socks and your Band Polo Shirt.&lt;/p&gt;
&lt;p&gt;As always, if you have any questions, please call:&lt;/p&gt;
 
&lt;p&gt;Amanda Kost – 440-864-6543 &lt;br&gt;Band Booster President&lt;/p&gt;</content>
  <ispublished>True</ispublished>
  <isdeleted>False</isdeleted>
  <iscommentsenabled>True</iscommentsenabled>
  <pubDate>2017-05-21 07:05:00</pubDate>
  <lastModified>2017-05-21 07:21:06</lastModified>
  <raters>0</raters>
  <rating>0</rating>
  <slug>band-t-shirt-band-polo-and-marching-band-shoe-purchase-info-and-more</slug>
  <tags />
  <comments />
  <categories>
    <category>8fccb9f0-4993-489b-b231-4593baca27ee</category>
  </categories>
  <notifications />
</post>