<?xml version="1.0" encoding="utf-8" standalone="yes"?>
<post>
  <author>Admin</author>
  <title>States Performance Times &amp; Volunteer Request</title>
  <description>Hi Band Families,
 
Mr. Vitale has updated his website with important information.  Please see his D</description>
  <content>Hi Band Families,
 
&lt;p&gt;Mr. Vitale has updated his website with important information.  Please see his &lt;a href="http://northroyaltonhighschoolband.com/director-s-notes.html."&gt;Director’s Notes page.&lt;/a&gt; &lt;/p&gt;
 
&lt;p&gt;He has posted information on States on the Performances page of his website. Here is a quick list of performance times on April 22 (Friday) and April 23 (Saturday).&lt;/p&gt;
&lt;ul&gt;
&lt;li&gt;Freshman Band - 8:00 AM - Saturday - Gym Stage&lt;/li&gt;
&lt;li&gt;Concert Band - 4:00 PM - Friday - Gym Stage&lt;/li&gt;
&lt;li&gt;Symphonic Band - 9:20 PM - Friday - Gym Stage&lt;/li&gt;
&lt;li&gt;Wind Ensemble - 7:50 PM - Friday - Auditorium Stage&lt;/li&gt;
 &lt;/ul&gt;
&lt;p&gt;We still need volunteers for States on April 22 &amp;amp; 23 and for Easter Seals on April 23. We are hoping that more of you can sign up now that the schedules have been posted. If you can help out please click the links below to sign up.&lt;/p&gt;
&lt;p&gt;&lt;a href="http://www.signupgenius.com/go/805054eafa729a02-omea"&gt;States Sign Up&lt;/a&gt;&lt;/p&gt;
&lt;p&gt;&lt;a href="http://www.signupgenius.com/go/805054eafa729a02-easter1"&gt;Easter Seals Sign Up&lt;/a&gt; &lt;/p&gt;
 
&lt;p&gt;Thanks!&lt;/p&gt;
 
&lt;p&gt;Becky Humes
Communications Coordinator&lt;/p&gt;</content>
  <ispublished>True</ispublished>
  <isdeleted>False</isdeleted>
  <iscommentsenabled>True</iscommentsenabled>
  <pubDate>2016-04-13 18:04:00</pubDate>
  <lastModified>2016-04-13 18:43:20</lastModified>
  <raters>0</raters>
  <rating>0</rating>
  <slug>states-performance-times-and-volunteer-request</slug>
  <tags />
  <comments />
  <categories>
    <category>6d8a90b6-376d-4bfc-b998-4281154f0d7b</category>
    <category>fa6094d0-c8e0-4964-8deb-b6349a6dd281</category>
  </categories>
  <notifications />
</post>